rtl/data_memory.sv
module data_memory(

    input logic clk,

    input logic mem_write,
    input logic mem_read,

    input logic [31:0] addr,
    input logic [31:0] write_data,

    output logic [31:0] read_data

);

logic [31:0] mem [0:1023];


// Write
always_ff @(posedge clk) begin

    if(mem_write)

        mem[addr[11:2]] <= write_data;

end


// Read
always_comb begin

    if(mem_read)

        read_data = mem[addr[11:2]];

    else

        read_data = 32'd0;

end

endmodule

rtl/alu.sv
module alu(
  input  logic [31:0] a,
  input  logic [31:0] b,
  input  logic [2:0]  alu_control,
  output logic [31:0] result
);
  always_comb begin
    case(alu_control)
      3'b000: result = a + b;   // ADD / ADDI
      3'b001: result = a - b;   // SUB
      3'b010: result = ($signed(a) < $signed(b)) ? 32'd1 : 32'd0; // SLT
      3'b100: result = a ^ b;   // XOR
      3'b101: result = a >> b[4:0]; // SRL
      3'b110: result = a | b;   // OR
      3'b111: result = a & b;   // AND
      default: result = 32'd0;
    endcase
  end
endmodule

rtl/immediate_generator.sv
module immediate_generator(

    input logic [31:0] instruction,

    output logic [31:0] immediate

);

logic [6:0] opcode;

assign opcode = instruction[6:0];

always_comb begin

    case(opcode)

        // I-type
        7'b0010011,
        7'b0000011:
            immediate =
            {{20{instruction[31]}},
             instruction[31:20]};

        // S-type
        7'b0100011:
            immediate =
            {{20{instruction[31]}},
             instruction[31:25],
             instruction[11:7]};

        // B-type
        7'b1100011:
            immediate =
            {{20{instruction[31]}},
             instruction[7],
             instruction[30:25],
             instruction[11:8],
             1'b0};

        // J-type (JAL)
        7'b1101111:          
            immediate =
            {{11{instruction[31]}},
            instruction[31],
            instruction[19:12],
            instruction[20],
            instruction[30:21],
            1'b0};

        default:
            immediate = 32'd0;

    endcase

end

endmodule

rtl/register_file.sv
module register_file(
    input logic clk,

    input logic [4:0] rs1,
    input logic [4:0] rs2,

    output logic [31:0] rs1_data,
    output logic [31:0] rs2_data,

    input logic reg_write,
    input logic [4:0] rd,
    input logic [31:0] write_data
);

logic [31:0] regs [0:31];

// x0 is always zero
// Read with write-through forwarding
assign rs1_data = (rs1 == 0) ? 0 : regs[rs1];
assign rs2_data = (rs2 == 0) ? 0 : regs[rs2];

always_ff @(posedge clk) begin

    if(reg_write && rd != 0)
        regs[rd] <= write_data;

end

endmodule

rtl/control_unit.sv
module control_unit(

    input logic [6:0] opcode,
    input  logic [2:0] funct3,
    input  logic [6:0] funct7,  
    output logic reg_write,

    output logic mem_write,
    output logic mem_read,
    output logic branch,
    output logic jump,
    output logic [2:0] alu_control

);

always_comb begin

    // Default values
    reg_write = 0;
    mem_write = 0;
    mem_read = 0;
    branch = 0;
    jump = 0;
    alu_control = 3'b000;

    case(opcode)

        // I-Type (ADDI)
        7'b0010011: begin

            reg_write = 1;

            // ADD
            alu_control = 3'b000;

        end

        // R-Type
        7'b0110011: begin
    	   reg_write = 1;
           // SUB ka funct7 = 0100000, ADD ka = 0000000
           if (funct3 == 3'b000 && funct7 == 7'b0100000)
               alu_control = 3'b001; // SUB
           else
           alu_control = funct3; // ADD/AND/OR/XOR etc
        end
        
        // LW
        7'b0000011: begin

           reg_write = 1;

           mem_read = 1;

           alu_control = 3'b000;

        end


        // SW
        7'b0100011: begin

           reg_write = 0;

           mem_write = 1;

           alu_control = 3'b000;

       end

       7'b1100011: begin

           branch = 1;

       end
      
       // JAL
       7'b1101111: begin

           reg_write = 1;
           jump = 1;
      end

        default: begin

            reg_write = 0;

            alu_control = 3'b000;

        end

    endcase

end

endmodule

rtl/decoder.sv
module decoder(

    input logic [31:0] instruction,

    output logic [6:0] opcode,
    output logic [4:0] rd,
    output logic [2:0] funct3,

    output logic [4:0] rs1,
    output logic [4:0] rs2,

    output logic [6:0] funct7

);

always_comb begin

    opcode = instruction[6:0];

    rd = instruction[11:7];

    funct3 = instruction[14:12];

    rs1 = instruction[19:15];

    rs2 = instruction[24:20];

    funct7 = instruction[31:25];

end

endmodule

rtl/instruction_memory.sv
module instruction_memory(
    input logic [31:0] addr,
    output logic [31:0] instruction
);

logic [31:0] mem [0:1023];

initial begin
    $readmemh("tests/program.mem", mem);
end

assign instruction = mem[addr[11:2]];

endmodule

formal/verify_pc/src/pc.sv
module pc(
    input logic clk,
    input logic reset,
    input logic [31:0] next_pc,
    output logic [31:0] current_pc
);

always_ff @(posedge clk or posedge reset) begin
    if(reset)
        current_pc <= 32'h00000000;
    else
        current_pc <= next_pc;
end

endmodule

rtl/cpu_core.sv
module cpu_core(
    input logic clk,
    input logic reset
);

// PC
logic [31:0] pc_current;
logic [31:0] pc_next;

// Instruction
logic [31:0] instruction;

// Decoder
logic [6:0] opcode;
logic [4:0] rd;

logic [2:0] funct3;

logic [4:0] rs1;
logic [4:0] rs2;

logic [6:0] funct7;

// Control
logic reg_write;
logic mem_write;
logic mem_read;
logic branch;
logic jump;
logic [2:0] alu_control;

// Register file
logic [31:0] rs1_data;
logic [31:0] rs2_data;


logic [31:0] mem_read_data;

// ALU
logic [31:0] alu_result;
logic [31:0] immediate;
logic [31:0] alu_b;
logic [31:0] memory_read_data;

// Next PC
assign pc_next =
    (jump) ? (pc_current + immediate) :
    (branch && (rs1_data == rs2_data)) ? (pc_current + immediate) :
    (pc_current + 4);

// PC
pc pc_inst(
    .clk(clk),
    .reset(reset),

    .next_pc(pc_next),
    .current_pc(pc_current)
);


// Instruction memory
instruction_memory imem_inst(
    .addr(pc_current),
    .instruction(instruction)
);


// Decoder
decoder decoder_inst(
    .instruction(instruction),

    .opcode(opcode),
    .rd(rd),

    .funct3(funct3),
    .funct7(funct7),  
    .rs1(rs1),
    .rs2(rs2)
    
);


// Control
control_unit control_inst(
    .opcode(opcode),
    .funct3(funct3),
    .funct7(funct7),   
    .reg_write(reg_write),
    .mem_write(mem_write),
    .mem_read(mem_read),
    .branch(branch),
    .jump(jump),
    .alu_control(alu_control)
);


// Register file
register_file rf_inst(

    .clk(clk),

    .rs1(rs1),
    .rs2(rs2),

    .rs1_data(rs1_data),
    .rs2_data(rs2_data),

    .reg_write(reg_write),

    .rd(rd),
    .write_data(alu_result)
);

// Immediate Generator
immediate_generator imm_gen_inst(

    .instruction(instruction),

    .immediate(immediate)

);

// 4-stage forwarding pipeline
logic [31:0] fwd_result_1, fwd_result_2, fwd_result_3, fwd_result_4;
logic [4:0]  fwd_rd_1, fwd_rd_2, fwd_rd_3, fwd_rd_4;
logic        fwd_we_1, fwd_we_2, fwd_we_3, fwd_we_4;

always_ff @(posedge clk) begin
    fwd_result_1 <= alu_result;  fwd_rd_1 <= rd;  fwd_we_1 <= reg_write;
    fwd_result_2 <= fwd_result_1; fwd_rd_2 <= fwd_rd_1; fwd_we_2 <= fwd_we_1;
    fwd_result_3 <= fwd_result_2; fwd_rd_3 <= fwd_rd_2; fwd_we_3 <= fwd_we_2;
    fwd_result_4 <= fwd_result_3; fwd_rd_4 <= fwd_rd_3; fwd_we_4 <= fwd_we_3;
end

logic [31:0] rs1_fwd, rs2_fwd;

always_comb begin
    // rs1 forwarding - nearest match wins
    if      (fwd_we_1 && fwd_rd_1 == rs1 && fwd_rd_1 != 0) rs1_fwd = fwd_result_1;
    else if (fwd_we_2 && fwd_rd_2 == rs1 && fwd_rd_2 != 0) rs1_fwd = fwd_result_2;
    else if (fwd_we_3 && fwd_rd_3 == rs1 && fwd_rd_3 != 0) rs1_fwd = fwd_result_3;
    else if (fwd_we_4 && fwd_rd_4 == rs1 && fwd_rd_4 != 0) rs1_fwd = fwd_result_4;
    else rs1_fwd = rs1_data;

    // rs2 forwarding
    if      (fwd_we_1 && fwd_rd_1 == rs2 && fwd_rd_1 != 0) rs2_fwd = fwd_result_1;
    else if (fwd_we_2 && fwd_rd_2 == rs2 && fwd_rd_2 != 0) rs2_fwd = fwd_result_2;
    else if (fwd_we_3 && fwd_rd_3 == rs2 && fwd_rd_3 != 0) rs2_fwd = fwd_result_3;
    else if (fwd_we_4 && fwd_rd_4 == rs2 && fwd_rd_4 != 0) rs2_fwd = fwd_result_4;
    else rs2_fwd = rs2_data;
end

// ALU source select
assign alu_b = (opcode == 7'b0110011) ? rs2_fwd : immediate;

//ALU
alu alu_inst(
    .a(rs1_fwd),
    .b(alu_b),
    .alu_control(alu_control),
    .result(alu_result)
);

// Data memory
data_memory dmem_inst(

    .clk(clk),

    .mem_write(mem_write),
    .mem_read(mem_read),

    .addr(alu_result),

    .write_data(rs2_data),

    .read_data(mem_read_data)

);

always_ff @(negedge clk) begin
  $display("PC=%h | INST=%h | RD=%0d | ALU=%0d",
    pc_current, instruction, rd, alu_result);
end

endmodule

tb/cpu_core_tb.sv
module cpu_core_tb;
logic clk;
logic reset;

always #5 clk = ~clk;

cpu_core dut(
    .clk(clk),
    .reset(reset)
);

initial begin
    $dumpfile("waves.vcd");
    $dumpvars(0, cpu_core_tb);
    clk = 0;
    reset = 1;
    #10;
    reset = 0;
    #350;
    $finish;
end
endmodule

waves.vcd
$version Generated by VerilatedVcd $end
$timescale 1ps $end
 $scope module $rootio $end
 $upscope $end
 $scope module cpu_core_tb $end
  $var wire 1 e clk $end
  $var wire 1 f reset $end
  $scope module dut $end
   $var wire 1 e clk $end
   $var wire 1 f reset $end
   $var wire 32 O pc_current [31:0] $end
   $var wire 32 P pc_next [31:0] $end
   $var wire 32 Q instruction [31:0] $end
   $var wire 7 R opcode [6:0] $end
   $var wire 5 S rd [4:0] $end
   $var wire 3 T funct3 [2:0] $end
   $var wire 5 U rs1 [4:0] $end
   $var wire 5 V rs2 [4:0] $end
   $var wire 7 W funct7 [6:0] $end
   $var wire 1 X reg_write $end
   $var wire 1 Y mem_write $end
   $var wire 1 Z mem_read $end
   $var wire 1 [ branch $end
   $var wire 1 \ jump $end
   $var wire 3 ] alu_control [2:0] $end
   $var wire 32 ^ rs1_data [31:0] $end
   $var wire 32 _ rs2_data [31:0] $end
   $var wire 32 g mem_read_data [31:0] $end
   $var wire 32 ` alu_result [31:0] $end
   $var wire 32 a immediate [31:0] $end
   $var wire 32 b alu_b [31:0] $end
   $var wire 32 i memory_read_data [31:0] $end
   $var wire 32 # fwd_result_1 [31:0] $end
   $var wire 32 $ fwd_result_2 [31:0] $end
   $var wire 32 % fwd_result_3 [31:0] $end
   $var wire 32 & fwd_result_4 [31:0] $end
   $var wire 5 ' fwd_rd_1 [4:0] $end
   $var wire 5 ( fwd_rd_2 [4:0] $end
   $var wire 5 ) fwd_rd_3 [4:0] $end
   $var wire 5 * fwd_rd_4 [4:0] $end
   $var wire 1 + fwd_we_1 $end
   $var wire 1 , fwd_we_2 $end
   $var wire 1 - fwd_we_3 $end
   $var wire 1 . fwd_we_4 $end
   $var wire 32 c rs1_fwd [31:0] $end
   $var wire 32 h rs2_fwd [31:0] $end
   $scope module alu_inst $end
    $var wire 32 c a [31:0] $end
    $var wire 32 b b [31:0] $end
    $var wire 3 ] alu_control [2:0] $end
    $var wire 32 ` result [31:0] $end
   $upscope $end
   $scope module control_inst $end
    $var wire 7 R opcode [6:0] $end
    $var wire 3 T funct3 [2:0] $end
    $var wire 7 W funct7 [6:0] $end
    $var wire 1 X reg_write $end
    $var wire 1 Y mem_write $end
    $var wire 1 Z mem_read $end
    $var wire 1 [ branch $end
    $var wire 1 \ jump $end
    $var wire 3 ] alu_control [2:0] $end
   $upscope $end
   $scope module decoder_inst $end
    $var wire 32 Q instruction [31:0] $end
    $var wire 7 R opcode [6:0] $end
    $var wire 5 S rd [4:0] $end
    $var wire 3 T funct3 [2:0] $end
    $var wire 5 U rs1 [4:0] $end
    $var wire 5 V rs2 [4:0] $end
    $var wire 7 W funct7 [6:0] $end
   $upscope $end
   $scope module dmem_inst $end
    $var wire 1 e clk $end
    $var wire 1 Y mem_write $end
    $var wire 1 Z mem_read $end
    $var wire 32 ` addr [31:0] $end
    $var wire 32 _ write_data [31:0] $end
    $var wire 32 g read_data [31:0] $end
   $upscope $end
   $scope module imem_inst $end
    $var wire 32 O addr [31:0] $end
    $var wire 32 Q instruction [31:0] $end
   $upscope $end
   $scope module imm_gen_inst $end
    $var wire 32 Q instruction [31:0] $end
    $var wire 32 a immediate [31:0] $end
    $var wire 7 d opcode [6:0] $end
   $upscope $end
   $scope module pc_inst $end
    $var wire 1 e clk $end
    $var wire 1 f reset $end
    $var wire 32 P next_pc [31:0] $end
    $var wire 32 O current_pc [31:0] $end
   $upscope $end
   $scope module rf_inst $end
    $var wire 1 e clk $end
    $var wire 5 U rs1 [4:0] $end
    $var wire 5 V rs2 [4:0] $end
    $var wire 32 ^ rs1_data [31:0] $end
    $var wire 32 _ rs2_data [31:0] $end
    $var wire 1 X reg_write $end
    $var wire 5 S rd [4:0] $end
    $var wire 32 ` write_data [31:0] $end
    $var wire 32 / regs[0] [31:0] $end
    $var wire 32 0 regs[1] [31:0] $end
    $var wire 32 1 regs[2] [31:0] $end
    $var wire 32 2 regs[3] [31:0] $end
    $var wire 32 3 regs[4] [31:0] $end
    $var wire 32 4 regs[5] [31:0] $end
    $var wire 32 5 regs[6] [31:0] $end
    $var wire 32 6 regs[7] [31:0] $end
    $var wire 32 7 regs[8] [31:0] $end
    $var wire 32 8 regs[9] [31:0] $end
    $var wire 32 9 regs[10] [31:0] $end
    $var wire 32 : regs[11] [31:0] $end
    $var wire 32 ; regs[12] [31:0] $end
    $var wire 32 < regs[13] [31:0] $end
    $var wire 32 = regs[14] [31:0] $end
    $var wire 32 > regs[15] [31:0] $end
    $var wire 32 ? regs[16] [31:0] $end
    $var wire 32 @ regs[17] [31:0] $end
    $var wire 32 A regs[18] [31:0] $end
    $var wire 32 B regs[19] [31:0] $end
    $var wire 32 C regs[20] [31:0] $end
    $var wire 32 D regs[21] [31:0] $end
    $var wire 32 E regs[22] [31:0] $end
    $var wire 32 F regs[23] [31:0] $end
    $var wire 32 G regs[24] [31:0] $end
    $var wire 32 H regs[25] [31:0] $end
    $var wire 32 I regs[26] [31:0] $end
    $var wire 32 J regs[27] [31:0] $end
    $var wire 32 K regs[28] [31:0] $end
    $var wire 32 L regs[29] [31:0] $end
    $var wire 32 M regs[30] [31:0] $end
    $var wire 32 N regs[31] [31:0] $end
   $upscope $end
  $upscope $end
 $upscope $end
$enddefinitions $end


#0
b00000000000000000000000000000000 #
b00000000000000000000000000000000 $
b00000000000000000000000000000000 %
b00000000000000000000000000000000 &
b00000 '
b00000 (
b00000 )
b00000 *
0+
0,
0-
0.
b00000000000000000000000000000000 /
b00000000000000000000000000000000 0
b00000000000000000000000000000000 1
b00000000000000000000000000000000 2
b00000000000000000000000000000000 3
b00000000000000000000000000000000 4
b00000000000000000000000000000000 5
b00000000000000000000000000000000 6
b00000000000000000000000000000000 7
b00000000000000000000000000000000 8
b00000000000000000000000000000000 9
b00000000000000000000000000000000 :
b00000000000000000000000000000000 ;
b00000000000000000000000000000000 <
b00000000000000000000000000000000 =
b00000000000000000000000000000000 >
b00000000000000000000000000000000 ?
b00000000000000000000000000000000 @
b00000000000000000000000000000000 A
b00000000000000000000000000000000 B
b00000000000000000000000000000000 C
b00000000000000000000000000000000 D
b00000000000000000000000000000000 E
b00000000000000000000000000000000 F
b00000000000000000000000000000000 G
b00000000000000000000000000000000 H
b00000000000000000000000000000000 I
b00000000000000000000000000000000 J
b00000000000000000000000000000000 K
b00000000000000000000000000000000 L
b00000000000000000000000000000000 M
b00000000000000000000000000000000 N
b00000000000000000000000000000000 O
b00000000000000000000000000000100 P
b00000000000000000000000000010011 Q
b0010011 R
b00000 S
b000 T
b00000 U
b00000 V
b0000000 W
1X
0Y
0Z
0[
0\
b000 ]
b00000000000000000000000000000000 ^
b00000000000000000000000000000000 _
b00000000000000000000000000000000 `
b00000000000000000000000000000000 a
b00000000000000000000000000000000 b
b00000000000000000000000000000000 c
b0010011 d
0e
1f
b00000000000000000000000000000000 g
b00000000000000000000000000000000 h
b00000000000000000000000000000000 i
#5
1+
1e
#10
0e
0f
#15
1,
b00000000000000000000000000000100 O
b00000000000000000000000000001000 P
b00000000010100000000000010010011 Q
b00001 S
b00101 V
b00000000000000000000000000000101 `
b00000000000000000000000000000101 a
b00000000000000000000000000000101 b
1e
#20
0e
#25
b00000000000000000000000000000101 #
b00001 '
1-
b00000000000000000000000000000101 0
b00000000000000000000000000001000 O
b00000000000000000000000000001100 P
b00000000000000000000000000010011 Q
b00000 S
b00000 V
b00000000000000000000000000000000 `
b00000000000000000000000000000000 a
b00000000000000000000000000000000 b
1e
#30
0e
#35
b00000000000000000000000000000000 #
b00000000000000000000000000000101 $
b00000 '
b00001 (
1.
b00000000000000000000000000001100 O
b00000000000000000000000000010000 P
1e
#40
0e
#45
b00000000000000000000000000000000 $
b00000000000000000000000000000101 %
b00000 (
b00001 )
b00000000000000000000000000010000 O
b00000000000000000000000000010100 P
1e
#50
0e
#55
b00000000000000000000000000000000 %
b00000000000000000000000000000101 &
b00000 )
b00001 *
b00000000000000000000000000010100 O
b00000000000000000000000000011000 P
1e
#60
0e
#65
b00000000000000000000000000000000 &
b00000 *
b00000000000000000000000000011000 O
b00000000000000000000000000011100 P
b00000000001100000000000100010011 Q
b00010 S
b00011 V
b00000000000000000000000000000011 `
b00000000000000000000000000000011 a
b00000000000000000000000000000011 b
1e
#70
0e
#75
b00000000000000000000000000000011 #
b00010 '
b00000000000000000000000000000011 1
b00000000000000000000000000011100 O
b00000000000000000000000000100000 P
b00000000000000000000000000010011 Q
b00000 S
b00000 V
b00000000000000000000000000000000 `
b00000000000000000000000000000000 a
b00000000000000000000000000000000 b
1e
#80
0e
#85
b00000000000000000000000000000000 #
b00000000000000000000000000000011 $
b00000 '
b00010 (
b00000000000000000000000000100000 O
b00000000000000000000000000100100 P
1e
#90
0e
#95
b00000000000000000000000000000000 $
b00000000000000000000000000000011 %
b00000 (
b00010 )
b00000000000000000000000000100100 O
b00000000000000000000000000101000 P
1e
#100
0e
#105
b00000000000000000000000000000000 %
b00000000000000000000000000000011 &
b00000 )
b00010 *
b00000000000000000000000000101000 O
b00000000000000000000000000101100 P
1e
#110
0e
#115
b00000000000000000000000000000000 &
b00000 *
b00000000000000000000000000101100 O
b00000000000000000000000000110000 P
b00000000001000001000001010110011 Q
b0110011 R
b00101 S
b00001 U
b00010 V
b00000000000000000000000000000101 ^
b00000000000000000000000000000011 _
b00000000000000000000000000001000 `
b00000000000000000000000000000011 b
b00000000000000000000000000000101 c
b0110011 d
1e
b00000000000000000000000000000011 h
#120
0e
#125
b00000000000000000000000000001000 #
b00101 '
b00000000000000000000000000001000 4
b00000000000000000000000000110000 O
b00000000000000000000000000110100 P
b00000000000000000000000000010011 Q
b0010011 R
b00000 S
b00000 U
b00000 V
b00000000000000000000000000000000 ^
b00000000000000000000000000000000 _
b00000000000000000000000000000000 `
b00000000000000000000000000000000 b
b00000000000000000000000000000000 c
b0010011 d
1e
b00000000000000000000000000000000 h
#130
0e
#135
b00000000000000000000000000000000 #
b00000000000000000000000000001000 $
b00000 '
b00101 (
b00000000000000000000000000110100 O
b00000000000000000000000000111000 P
1e
#140
0e
#145
b00000000000000000000000000000000 $
b00000000000000000000000000001000 %
b00000 (
b00101 )
b00000000000000000000000000111000 O
b00000000000000000000000000111100 P
1e
#150
0e
#155
b00000000000000000000000000000000 %
b00000000000000000000000000001000 &
b00000 )
b00101 *
b00000000000000000000000000111100 O
b00000000000000000000000001000000 P
1e
#160
0e
#165
b00000000000000000000000000000000 &
b00000 *
b00000000000000000000000001000000 O
b00000000000000000000000001000100 P
b01000000001000001000001100110011 Q
b0110011 R
b00110 S
b00001 U
b00010 V
b0100000 W
b001 ]
b00000000000000000000000000000101 ^
b00000000000000000000000000000011 _
b00000000000000000000000000000010 `
b00000000000000000000000000000011 b
b00000000000000000000000000000101 c
b0110011 d
1e
b00000000000000000000000000000011 h
#170
0e
#175
b00000000000000000000000000000010 #
b00110 '
b00000000000000000000000000000010 5
b00000000000000000000000001000100 O
b00000000000000000000000001001000 P
b00000000000000000000000000010011 Q
b0010011 R
b00000 S
b00000 U
b00000 V
b0000000 W
b000 ]
b00000000000000000000000000000000 ^
b00000000000000000000000000000000 _
b00000000000000000000000000000000 `
b00000000000000000000000000000000 b
b00000000000000000000000000000000 c
b0010011 d
1e
b00000000000000000000000000000000 h
#180
0e
#185
b00000000000000000000000000000000 #
b00000000000000000000000000000010 $
b00000 '
b00110 (
b00000000000000000000000001001000 O
b00000000000000000000000001001100 P
1e
#190
0e
#195
b00000000000000000000000000000000 $
b00000000000000000000000000000010 %
b00000 (
b00110 )
b00000000000000000000000001001100 O
b00000000000000000000000001010000 P
1e
#200
0e
#205
b00000000000000000000000000000000 %
b00000000000000000000000000000010 &
b00000 )
b00110 *
b00000000000000000000000001010000 O
b00000000000000000000000001010100 P
1e
#210
0e
#215
b00000000000000000000000000000000 &
b00000 *
b00000000000000000000000001010100 O
b00000000000000000000000001011000 P
b00000000001000001111001110110011 Q
b0110011 R
b00111 S
b111 T
b00001 U
b00010 V
b111 ]
b00000000000000000000000000000101 ^
b00000000000000000000000000000011 _
b00000000000000000000000000000001 `
b00000000000000000000000000000011 b
b00000000000000000000000000000101 c
b0110011 d
1e
b00000000000000000000000000000011 h
#220
0e
#225
b00000000000000000000000000000001 #
b00111 '
b00000000000000000000000000000001 6
b00000000000000000000000001011000 O
b00000000000000000000000001011100 P
b00000000000000000000000000010011 Q
b0010011 R
b00000 S
b000 T
b00000 U
b00000 V
b000 ]
b00000000000000000000000000000000 ^
b00000000000000000000000000000000 _
b00000000000000000000000000000000 `
b00000000000000000000000000000000 b
b00000000000000000000000000000000 c
b0010011 d
1e
b00000000000000000000000000000000 h
#230
0e
#235
b00000000000000000000000000000000 #
b00000000000000000000000000000001 $
b00000 '
b00111 (
b00000000000000000000000001011100 O
b00000000000000000000000001100000 P
1e
#240
0e
#245
b00000000000000000000000000000000 $
b00000000000000000000000000000001 %
b00000 (
b00111 )
b00000000000000000000000001100000 O
b00000000000000000000000001100100 P
1e
#250
0e
#255
b00000000000000000000000000000000 %
b00000000000000000000000000000001 &
b00000 )
b00111 *
b00000000000000000000000001100100 O
b00000000000000000000000001101000 P
1e
#260
0e
#265
b00000000000000000000000000000000 &
b00000 *
b00000000000000000000000001101000 O
b00000000000000000000000001101100 P
b00000000001000001110010000110011 Q
b0110011 R
b01000 S
b110 T
b00001 U
b00010 V
b110 ]
b00000000000000000000000000000101 ^
b00000000000000000000000000000011 _
b00000000000000000000000000000111 `
b00000000000000000000000000000011 b
b00000000000000000000000000000101 c
b0110011 d
1e
b00000000000000000000000000000011 h
#270
0e
#275
b00000000000000000000000000000111 #
b01000 '
b00000000000000000000000000000111 7
b00000000000000000000000001101100 O
b00000000000000000000000001110000 P
b00000000000000000000000000000000 Q
b0000000 R
b00000 S
b000 T
b00000 U
b00000 V
0X
b000 ]
b00000000000000000000000000000000 ^
b00000000000000000000000000000000 _
b00000000000000000000000000000000 `
b00000000000000000000000000000000 b
b00000000000000000000000000000000 c
b0000000 d
1e
b00000000000000000000000000000000 h
#280
0e
#285
b00000000000000000000000000000000 #
b00000000000000000000000000000111 $
b00000 '
b01000 (
0+
b00000000000000000000000001110000 O
b00000000000000000000000001110100 P
1e
#290
0e
#295
b00000000000000000000000000000000 $
b00000000000000000000000000000111 %
b00000 (
b01000 )
0,
b00000000000000000000000001110100 O
b00000000000000000000000001111000 P
1e
#300
0e
#305
b00000000000000000000000000000000 %
b00000000000000000000000000000111 &
b00000 )
b01000 *
0-
b00000000000000000000000001111000 O
b00000000000000000000000001111100 P
1e
#310
0e
#315
b00000000000000000000000000000000 &
b00000 *
0.
b00000000000000000000000001111100 O
b00000000000000000000000010000000 P
1e
#320
0e
#325
b00000000000000000000000010000000 O
b00000000000000000000000010000100 P
1e
#330
0e
#335
b00000000000000000000000010000100 O
b00000000000000000000000010001000 P
1e
#340
0e
#345
b00000000000000000000000010001000 O
b00000000000000000000000010001100 P
1e
#350
0e
#355
b00000000000000000000000010001100 O
b00000000000000000000000010010000 P
1e
